mkdocs_blueprintue/__init__.py
mkdocs_blueprintue/assets/bue-render/copy-button.css
mkdocs_blueprintue/assets/bue-render/copy-button.js
mkdocs_blueprintue/assets/bue-render/render.css
mkdocs_blueprintue/assets/bue-render/render.js
mkdocs_blueprintue-0.1.4.dist-info/LICENSE
mkdocs_blueprintue-0.1.4.dist-info/METADATA
mkdocs_blueprintue-0.1.4.dist-info/WHEEL
mkdocs_blueprintue-0.1.4.dist-info/entry_points.txt
mkdocs_blueprintue-0.1.4.dist-info/top_level.txt
mkdocs_blueprintue-0.1.4.dist-info/RECORD
