Metadata-Version: 2.1
Name: mkdocs-blueprintue
Version: 0.1.4
Summary: MkDocs plugin for rendering Unreal Engine Blueprint nodes
Home-page: https://github.com/kisspread/uebp
Author: kisspread
Author-email: kisspread@users.noreply.github.com
License: MIT
Keywords: mkdocs plugin blueprint unreal engine
Classifier: Development Status :: 4 - Beta
Classifier: Intended Audience :: Developers
Classifier: Intended Audience :: Information Technology
Classifier: License :: OSI Approved :: MIT License
Classifier: Programming Language :: Python
Classifier: Programming Language :: Python :: 3 :: Only
Classifier: Programming Language :: Python :: 3.6
Classifier: Programming Language :: Python :: 3.7
Classifier: Programming Language :: Python :: 3.8
Classifier: Programming Language :: Python :: 3.9
Requires-Python: >=3.6
License-File: LICENSE
Requires-Dist: mkdocs>=1.0.4
